testproject/test.v
module mux2x1_behaviroal_if_else (a0, a1, s, y);
    input s, a0, a1;
    output y;
    reg y ;
    always @ (*) begin
        if (s)begin
            y = a1;
        end else begin
            y = a0;
        end
    end
endmodule

testproject/fuck.v
`include "test.v"
module test_you;

    reg s,a0,a1;
    wire y;
    mux2x1_behaviroal_if_else t1(a0,a1,s,y);

    //test cases
    initial begin
            s = 0; a1 = 0; a0 = 0;
        #1  s = 0; a1 = 0; a0 = 1;
        #1  s = 0; a1 = 1; a0 = 0;
        #1  s = 0; a1 = 1; a0 = 1;
        #1  s = 1; a1 = 0; a0 = 0;
        #1  s = 1; a1 = 0; a0 = 1;
        #1  s = 1; a1 = 1; a0 = 0;
        #1  s = 1; a1 = 1; a0 = 1;
        #1  s = 0; a1 = 0; a0 = 0;
        #1 $finish;
    end
    initial begin
        $monitor ($time, ":\ts = %b\ta1 = %b\ta0 = %b\ty = %b",
                    s, a1, a0, y);
        $dumpfile("test_test.vcd");
        $dumpvars;
    end
endmodule

testproject/test_test.vcd
$date
	Fri Oct 05 18:04:18 2018
$end
$version
	Icarus Verilog
$end
$timescale
	1s
$end
$scope module test_you $end
$var wire 1 ! y $end
$var reg 1 " a0 $end
$var reg 1 # a1 $end
$var reg 1 $ s $end
$scope module t1 $end
$var wire 1 " a0 $end
$var wire 1 # a1 $end
$var wire 1 $ s $end
$var reg 1 ! y $end
$upscope $end
$upscope $end
$enddefinitions $end
#0
$dumpvars
0$
0#
0"
0!
$end
#1
1!
1"
#2
0!
0"
1#
#3
1!
1"
#4
0!
0"
0#
1$
#5
1"
#6
1!
0"
1#
#7
1"
#8
0!
0"
0#
0$
